pomlock/__init__.py
pomlock/app.py
pomlock/constants.py
pomlock/custom_rich_handler.py
pomlock/input_handler.py
pomlock/log_render.py
pomlock/logger.py
pomlock/utils.py
pomlock/waybar.py
pomlock-2.0.0.dist-info/licenses/LICENSE
pomlock-2.0.0.dist-info/WHEEL
pomlock-2.0.0.dist-info/entry_points.txt
pomlock-2.0.0.dist-info/METADATA
pomlock-2.0.0.dist-info/RECORD
