Metadata-Version: 2.4
Name: pomlock
Version: 2.0.0
Summary: A Linux utility that enforces regular breaks by temporarily blocking input devices
Keywords: pomodoro,timer,productivity,focus,linux,cli,input-blocker,break-timer,time-management
Author: Luis Cadillo
Author-email: Luis Cadillo <luiscaf3r@gmail.com>
License-Expression: MIT
License-File: LICENSE
Classifier: Intended Audience :: End Users/Desktop
Classifier: Programming Language :: Python :: 3
Classifier: Operating System :: POSIX :: Linux
Classifier: Topic :: Utilities
Requires-Dist: rich
Requires-Dist: rich-argparse>=1.7.1
Requires-Python: >=3.9
Project-URL: Issues, https://github.com/luiisca/pomlock/issues
Project-URL: Repository, https://github.com/luiisca/pomlock
